LICENSE
MANIFEST.in
README.md
README_zh.md
pyproject.toml
src/fcs_order.egg-info/PKG-INFO
src/fcs_order.egg-info/SOURCES.txt
src/fcs_order.egg-info/dependency_links.txt
src/fcs_order.egg-info/entry_points.txt
src/fcs_order.egg-info/requires.txt
src/fcs_order.egg-info/top_level.txt
src/fcsorder/__init__.py
src/fcsorder/calc/__init__.py
src/fcsorder/calc/calculators.py
src/fcsorder/calc/mtp2calc.py
src/fcsorder/commands/__init__.py
src/fcsorder/commands/mlp3.py
src/fcsorder/commands/mlp4.py
src/fcsorder/commands/reap.py
src/fcsorder/commands/sow.py
src/fcsorder/core/__init__.py
src/fcsorder/core/fourthorder_core.py
src/fcsorder/core/thirdorder_core.py
src/fcsorder/core/domain/__init__.py
src/fcsorder/core/domain/common.py
src/fcsorder/core/domain/gaussian.py
src/fcsorder/core/domain/symmetry.py
src/fcsorder/core/domain/wedge3.py
src/fcsorder/core/domain/wedge4.py
src/fcsorder/io/__init__.py
src/fcsorder/io/io_abstraction.py
src/fcsorder/phonon/__init__.py
src/fcsorder/phonon/generate_phonon_rattled_structures.py
src/fcsorder/phonon/mlp2.py
src/fcsorder/phonon/scph.py
src/fcsorder/phonon/domain/__init__.py
src/fcsorder/phonon/domain/secondorder_core.py
src/fcsorder/phonon/domain/self_consistent_phonons.py