Metadata-Version: 2.4
Name: fcs-order
Version: 4.0.0
Summary: Extract 2nd-, 3rd-, and 4th-order force constants using arbitrary machine-learning potentials; compatible with the original thirdorder and fourthorder sow and reap commands
License: Apache License
Requires-Python: <3.14,>=3.9
License-File: LICENSE
Requires-Dist: ase
Requires-Dist: matplotlib
Requires-Dist: numba
Requires-Dist: numpy
Requires-Dist: scipy
Requires-Dist: sparse
Requires-Dist: spglib
Requires-Dist: typer
Provides-Extra: calorine
Requires-Dist: calorine; extra == "calorine"
Provides-Extra: deepmd
Requires-Dist: deepmd-kit; extra == "deepmd"
Provides-Extra: hiphive
Requires-Dist: hiphive; extra == "hiphive"
Provides-Extra: mlp
Requires-Dist: pypolymlp; extra == "mlp"
Provides-Extra: tace
Requires-Dist: tace; extra == "tace"
Provides-Extra: all
Requires-Dist: calorine; extra == "all"
Requires-Dist: deepmd-kit; extra == "all"
Requires-Dist: hiphive; extra == "all"
Requires-Dist: pypolymlp; extra == "all"
Requires-Dist: tace; extra == "all"
Dynamic: license-file
